picker/__init__.py
picker/nose_plugin.py
picker/sample_multiprocess_script.py
nose_picker-0.5.6.dist-info/LICENSE
nose_picker-0.5.6.dist-info/METADATA
nose_picker-0.5.6.dist-info/WHEEL
nose_picker-0.5.6.dist-info/entry_points.txt
nose_picker-0.5.6.dist-info/top_level.txt
nose_picker-0.5.6.dist-info/zip-safe
nose_picker-0.5.6.dist-info/RECORD
