Metadata-Version: 2.1
Name: nose-picker
Version: 0.5.6
Summary: nose plugin that picks a subset of your unit tests
Home-page: https://github.com/eventbrite/nose-picker
License: BSD
Platform: UNKNOWN
Classifier: License :: OSI Approved :: BSD License
Classifier: Programming Language :: Python :: 2.6
Classifier: Programming Language :: Python :: 2.7
License-File: LICENSE
Requires-Dist: six (>=1.16)
